setup.py
HyREPL/__init__.hy
HyREPL/__init__.py
HyREPL/bencode.hy
HyREPL/ops.hy
HyREPL/server.hy
HyREPL/session.hy
HyREPL/workarounds.hy
HyREPL.egg-info/PKG-INFO
HyREPL.egg-info/SOURCES.txt
HyREPL.egg-info/dependency_links.txt
HyREPL.egg-info/requires.txt
HyREPL.egg-info/top_level.txt
bin/hyrepl