Metadata-Version: 1.1
Name: HyREPL
Version: 0.1.1
Summary: nREPL implementation in Hylang
Home-page: https://github.com/Foxboron/HyREPL
Author: Morten Linderud, Gregor Best
Author-email: morten@linderud.pw, gbe@unobtanium.de
License: MIT
Platform: any
Classifier: Development Status :: 3 - Alpha
Classifier: Intended Audience :: Developers
Classifier: Operating System :: OS Independent
Classifier: Programming Language :: Lisp
Classifier: Topic :: Software Development :: Libraries
